bytedminerva_sdk/__init__.py
bytedminerva_sdk-0.0.1.dist-info/METADATA
bytedminerva_sdk-0.0.1.dist-info/WHEEL
bytedminerva_sdk-0.0.1.dist-info/top_level.txt
bytedminerva_sdk-0.0.1.dist-info/RECORD
